artix_news-0.3.0.dist-info/METADATA
artix_news-0.3.0.dist-info/WHEEL
artix_news-0.3.0.dist-info/entry_points.txt
artix_news-0.3.0.dist-info/licenses/LICENSE
artix_news.py
artix_news-0.3.0.dist-info/RECORD
